README.md
setup.py
LVREML.egg-info/PKG-INFO
LVREML.egg-info/SOURCES.txt
LVREML.egg-info/dependency_links.txt
LVREML.egg-info/top_level.txt
lvreml/__init__.py
lvreml/data_prep.py
lvreml/initial_screen.py
lvreml/lvreml.py